LICENSE.txt
README.md
README.txt
setup.cfg
setup.py
instResp/__init__.py
instResp/libInst.py
instResp/libNom.py
instResp/plotResp.py
instResp/polezero.py
instResp.egg-info/PKG-INFO
instResp.egg-info/SOURCES.txt
instResp.egg-info/dependency_links.txt
instResp.egg-info/entry_points.txt
instResp.egg-info/not-zip-safe
instResp.egg-info/requires.txt
instResp.egg-info/top_level.txt